text2audio/__init__.py
text2audio/module.py
text2video/__init__.py
text2video/module.py
text2audio-0.0.1.dist-info/METADATA
text2audio-0.0.1.dist-info/WHEEL
text2audio-0.0.1.dist-info/top_level.txt
text2audio-0.0.1.dist-info/RECORD
